hargutil/__init__.py
hargutil-1.1.3.dist-info/LICENSE
hargutil-1.1.3.dist-info/METADATA
hargutil-1.1.3.dist-info/WHEEL
hargutil-1.1.3.dist-info/top_level.txt
hargutil-1.1.3.dist-info/RECORD
