Metadata-Version: 2.1
Name: hargutil
Version: 1.1.3
Summary: A simple arguments utility
Home-page: https://github.com/horange321/hargutil-python
Author: Horange
Author-email: horange321@163.com
License: UNKNOWN
Platform: UNKNOWN
Classifier: Programming Language :: Python :: 3
Classifier: License :: OSI Approved :: MIT License
Classifier: Operating System :: OS Independent
License-File: LICENSE
